setup.py
mtq/__init__.py
mtq/connection.py
mtq/defaults.py
mtq/errors.py
mtq/job.py
mtq/log.py
mtq/queue.py
mtq/schedule.py
mtq/utils.py
mtq/worker.py
mtq.egg-info/PKG-INFO
mtq.egg-info/SOURCES.txt
mtq.egg-info/dependency_links.txt
mtq.egg-info/entry_points.txt
mtq.egg-info/requires.txt
mtq.egg-info/top_level.txt
mtq/scripts/__init__.py
mtq/scripts/ctrl.py
mtq/scripts/info.py
mtq/scripts/log.py
mtq/scripts/schedule.py
mtq/scripts/worker.py
mtq/tests/__init__.py
mtq/tests/__main__.py
mtq/tests/fixture.py
mtq/tests/runtests.py
mtq/tests/test_job.py
mtq/tests/test_queue.py
mtq/tests/test_worker.py