Metadata-Version: 1.0
Name: mtq
Version: 0.3.1
Summary: Mongo Task Queue
Home-page: UNKNOWN
Author: Continuum Analytics
Author-email: sean.ross-ross@continuum.io
License: UNKNOWN
Platform: UNKNOWN
